fatf/__init__.py
fatf/exceptions.py
fatf/accountability/__init__.py
fatf/accountability/data/__init__.py
fatf/accountability/data/measures.py
fatf/accountability/models/__init__.py
fatf/accountability/models/measures.py
fatf/fairness/__init__.py
fatf/fairness/data/__init__.py
fatf/fairness/data/measures.py
fatf/fairness/models/__init__.py
fatf/fairness/models/measures.py
fatf/fairness/predictions/__init__.py
fatf/fairness/predictions/measures.py
fatf/transparency/__init__.py
fatf/transparency/data/__init__.py
fatf/transparency/data/describe_functions.py
fatf/transparency/models/__init__.py
fatf/transparency/models/feature_influence.py
fatf/transparency/models/submodular_pick.py
fatf/transparency/predictions/__init__.py
fatf/transparency/predictions/counterfactuals.py
fatf/transparency/predictions/surrogate_explainers.py
fatf/transparency/predictions/surrogate_image_explainers.py
fatf/transparency/sklearn/__init__.py
fatf/transparency/sklearn/linear_model.py
fatf/transparency/sklearn/tools.py
fatf/utils/__init__.py
fatf/utils/distances.py
fatf/utils/kernels.py
fatf/utils/tools.py
fatf/utils/validation.py
fatf/utils/array/__init__.py
fatf/utils/array/tools.py
fatf/utils/array/validation.py
fatf/utils/data/__init__.py
fatf/utils/data/augmentation.py
fatf/utils/data/datasets.py
fatf/utils/data/density.py
fatf/utils/data/discretisation.py
fatf/utils/data/instance_augmentation.py
fatf/utils/data/occlusion.py
fatf/utils/data/segmentation.py
fatf/utils/data/tools.py
fatf/utils/data/transformation.py
fatf/utils/data/datasets/health_records.csv
fatf/utils/data/datasets/iris.csv
fatf/utils/data/feature_selection/__init__.py
fatf/utils/data/feature_selection/sklearn.py
fatf/utils/metrics/__init__.py
fatf/utils/metrics/metrics.py
fatf/utils/metrics/subgroup_metrics.py
fatf/utils/metrics/tools.py
fatf/utils/models/__init__.py
fatf/utils/models/models.py
fatf/utils/models/processing.py
fatf/utils/models/validation.py
fatf/utils/testing/__init__.py
fatf/utils/testing/arrays.py
FAT_Forensics-0.1.2.dist-info/LICENCE
FAT_Forensics-0.1.2.dist-info/METADATA
FAT_Forensics-0.1.2.dist-info/WHEEL
FAT_Forensics-0.1.2.dist-info/top_level.txt
FAT_Forensics-0.1.2.dist-info/RECORD
