Metadata-Version: 2.1
Name: FAT-Forensics
Version: 0.1.2
Summary: A Python Toolbox for Algorithmic Fairness, Accountability and Transparency
Home-page: https://fat-forensics.org/
Maintainer: Kacper Sokol
Maintainer-email: k.sokol@bristol.ac.uk
License: new BSD
Download-URL: https://pypi.org/project/FAT-Forensics/#files
Platform: UNKNOWN
Requires-Python: ~=3.5
Requires-Dist: numpy (>=1.10.0)
Requires-Dist: scipy (>=0.13.3)
Provides-Extra: all
Requires-Dist: matplotlib (>=3.0.0) ; extra == 'all'
Requires-Dist: Pillow (>=8.4.0) ; extra == 'all'
Requires-Dist: scikit-image (>=0.17) ; extra == 'all'
Requires-Dist: scikit-learn (>=0.19.2) ; extra == 'all'
Provides-Extra: dev
Requires-Dist: codecov (==2.1.0) ; extra == 'dev'
Requires-Dist: docutils (<0.18) ; extra == 'dev'
Requires-Dist: flake8 (==3.8.1) ; extra == 'dev'
Requires-Dist: isort (<=4.3.21) ; extra == 'dev'
Requires-Dist: jinja2 (<3.1.0) ; extra == 'dev'
Requires-Dist: mypy (==0.770) ; extra == 'dev'
Requires-Dist: nbval (==0.9.1) ; extra == 'dev'
Requires-Dist: numpydoc (==0.8.0) ; extra == 'dev'
Requires-Dist: pylint (==2.3.0) ; extra == 'dev'
Requires-Dist: pytest (==3.9.1) ; extra == 'dev'
Requires-Dist: pytest-cov (==2.6.0) ; extra == 'dev'
Requires-Dist: sphinx (==2.0) ; extra == 'dev'
Requires-Dist: sphinx-gallery (==0.3.1) ; extra == 'dev'
Requires-Dist: twine (==1.14.0) ; extra == 'dev'
Requires-Dist: wheel ; extra == 'dev'
Requires-Dist: yapf (==0.26.0) ; extra == 'dev'
Provides-Extra: ml
Requires-Dist: scikit-learn (>=0.19.2) ; extra == 'ml'
Provides-Extra: vis
Requires-Dist: matplotlib (>=3.0.0) ; extra == 'vis'
